README.txt
setup.py
start-xcbl.py
xcbl/__init__.py
xcbl/controllers.py
xcbl/json.py
xcbl/model.py
xcbl/release.py
xcbl/widgets.py
xcbl.egg-info/PKG-INFO
xcbl.egg-info/SOURCES.txt
xcbl.egg-info/dependency_links.txt
xcbl.egg-info/entry_points.txt
xcbl.egg-info/not-zip-safe
xcbl.egg-info/paster_plugins.txt
xcbl.egg-info/requires.txt
xcbl.egg-info/sqlobject.txt
xcbl.egg-info/top_level.txt
xcbl/config/__init__.py
xcbl/templates/__init__.py
xcbl/tests/__init__.py
xcbl/tests/test_controllers.py
xcbl/tests/test_model.py
