Metadata-Version: 1.0
Name: xcbl
Version: 0.2
Summary: Extensible CheckBoxList widget for TurboGears
Home-page: http://catherine.devlin.googlepages.com/xcbl.html
Author: Catherine Devlin
Author-email: catherine.devlin@gmail.com
License: MIT
Download-URL: http://catherine.devlin.googlepages.com/xcbl.egg
Keywords: turbogears.widgets
Platform: UNKNOWN
Classifier: Development Status :: 3 - Alpha
Classifier: Operating System :: OS Independent
Classifier: Programming Language :: Python
Classifier: Topic :: Software Development :: Libraries :: Python Modules
Classifier: Framework :: TurboGears
Classifier: Framework :: TurboGears :: Widgets
